chatHelper/__init__.py
chatHelper/chat.py
chatHelper-1.1.9.dist-info/LICENSE
chatHelper-1.1.9.dist-info/METADATA
chatHelper-1.1.9.dist-info/WHEEL
chatHelper-1.1.9.dist-info/top_level.txt
chatHelper-1.1.9.dist-info/RECORD
