Metadata-Version: 2.1
Name: chatHelper
Version: 1.1.9
Summary: High-level chat client API that makes sending messages between computers(using http) easy.
Home-page: https://github.com/DudeBro249/ChatHelper-Python/
Author: WeServe Technologies
Author-email: appdevdeploy@gmail.com
License: UNKNOWN
Platform: UNKNOWN
Classifier: Programming Language :: Python :: 3
Classifier: License :: OSI Approved :: Apache Software License
Classifier: Operating System :: OS Independent
Requires-Python: >=3.5
Requires-Dist: Flask
Requires-Dist: requests
